LICENSE
README.md
setup.py
relmod/__init__.py
relmod/_version.py
relmod/autoimport.py
relmod/cache.py
relmod/fakesite.py
relmod/finder.py
relmod/fmods.py
relmod/proxy.py
relmod/registry.py
relmod/runner.py
relmod/utils.py
relmod.egg-info/PKG-INFO
relmod.egg-info/SOURCES.txt
relmod.egg-info/dependency_links.txt
relmod.egg-info/top_level.txt
relmod/tests/__init__.py
relmod/tests/test_func.py
relmod/tests/test_main.py
relmod/tests/test_runner.py
relmod/tests/tkfs.py