Metadata-Version: 2.1
Name: relmod
Version: 0.5.0
Summary: Auto-Reloadable Modules and Namespaces
Home-page: http://github.com/serwy/relmod
Author: Roger D. Serwy
Author-email: roger.serwy@gmail.com
License: BSD License
Keywords: reload module
Platform: Windows
Platform: Linux
Platform: Solaris
Platform: Mac OS-X
Platform: Unix
Classifier: Development Status :: 4 - Beta
Classifier: Intended Audience :: Developers
Classifier: License :: OSI Approved :: BSD License
Classifier: Operating System :: OS Independent
Classifier: Programming Language :: Python :: 3
Classifier: Topic :: Software Development :: Libraries
Classifier: Topic :: Software Development :: Testing :: Unit
License-File: LICENSE
